loremipsum/__init__.py
loremipsum/generator.py
loremipsum_pro-0.1.3.dist-info/METADATA
loremipsum_pro-0.1.3.dist-info/WHEEL
loremipsum_pro-0.1.3.dist-info/top_level.txt
loremipsum_pro-0.1.3.dist-info/RECORD
