Metadata-Version: 2.4
Name: loremipsum-pro
Version: 0.1.3
Summary: A lightweight Python library for generating Lorem Ipsum placeholder text with zero dependencies
Author: Lorem Ipsum Generator
License: MIT
Project-URL: Homepage, https://github.com/bearboy80/loremipsum-pro
Project-URL: Bug Tracker, https://github.com/bearboy80/loremipsum-pro/issues
Keywords: lorem,ipsum,placeholder,text,generator
Classifier: Programming Language :: Python :: 3
Classifier: License :: OSI Approved :: MIT License
Classifier: Operating System :: OS Independent
Requires-Python: >=3.8
Provides-Extra: dev
Requires-Dist: build; extra == "dev"
Requires-Dist: twine; extra == "dev"
